mbed_vscode_tools/__init__.py
mbed_vscode_tools/consts.py
mbed_vscode_tools/mbed_config_gen.py
mbed_vscode_tools/mbed_vscode_tools.py
mbed_vscode_tools-0.1.4.1.dist-info/LICENSE
mbed_vscode_tools-0.1.4.1.dist-info/METADATA
mbed_vscode_tools-0.1.4.1.dist-info/WHEEL
mbed_vscode_tools-0.1.4.1.dist-info/entry_points.txt
mbed_vscode_tools-0.1.4.1.dist-info/top_level.txt
mbed_vscode_tools-0.1.4.1.dist-info/RECORD
