Metadata-Version: 2.1
Name: mbed-vscode-tools
Version: 0.1.4.1
Summary: A command-line tool to help vscode intellisense for your mbed-os projects.
Home-page: https://github.com/sterngerlach/mbed-vscode-tools
Author: Keisuke Sugiura
Author-email: mineto.tsukada@gmail.com
License: MIT
Platform: UNKNOWN
Classifier: Programming Language :: Python :: 3 :: Only
Classifier: License :: OSI Approved :: MIT License
Classifier: Operating System :: POSIX :: Linux
Requires-Python: >=3.6
Requires-Dist: click (<8.0.0,>=7.0.0)
